{
  "name": "DMD2",
  "keywords": "DMD, DMD2, avr, sam, ESP8266, Display",
  "description": "Dot Matrix Display Library 2",
  "repository":
  {
    "type": "git",
    "url": "https://github.com/freetronics/DMD2.git"
  },
  "authors":
  [
    {
      "name": "Harrison Mclean",
      "maintainer": true
    },
    {
      "name": "Angus Gratton",
    },
    {
      "name": "Freetronics",
    },
  ],
  "version": "0.0.4",
  "frameworks": "arduino",
  "platforms": [
    "atmelavr",
    "atmelsam",
    "espressif8266"
  ]
}
